{
    "1": "https://www.work.ua/jobs/3816008/",
    "2": "https://www.work.ua/jobs/3539664/",
    "3": "https://www.work.ua/jobs/3792031/",
    "4": "https://www.work.ua/jobs/3815857/",
    "5": "https://www.work.ua/jobs/3803031/",
    "6": "https://www.work.ua/jobs/3804049/",
    "7": "https://www.work.ua/jobs/3815329/",
    "8": "https://www.work.ua/jobs/1337614/",
    "9": "https://www.work.ua/jobs/2983775/",
    "10": "https://www.work.ua/jobs/2751859/",
    "11": "https://www.work.ua/jobs/3699236/",
    "12": "https://www.work.ua/jobs/3815037/",
    "13": "https://www.work.ua/jobs/3814962/",
    "14": "https://www.work.ua/jobs/3760787/",
    "15": "https://www.work.ua/jobs/3720562/",
    "16": "https://www.work.ua/jobs/3660158/",
    "17": "https://www.work.ua/jobs/3703465/",
    "18": "https://www.work.ua/jobs/3803723/",
    "19": "https://www.work.ua/jobs/3814367/",
    "20": "https://www.work.ua/jobs/3814343/",
    "21": "https://www.work.ua/jobs/3801194/",
    "22": "https://www.work.ua/jobs/2140186/",
    "23": "https://www.work.ua/jobs/3803241/",
    "24": "https://www.work.ua/jobs/3309643/",
    "25": "https://www.work.ua/jobs/3381476/",
    "26": "https://www.work.ua/jobs/3798579/",
    "27": "https://www.work.ua/jobs/3823755/",
    "28": "https://www.work.ua/jobs/3801153/",
    "29": "https://www.work.ua/jobs/3506255/",
    "30": "https://www.work.ua/jobs/3823438/",
    "31": "https://www.work.ua/jobs/3744383/",
    "32": "https://www.work.ua/jobs/2870408/",
    "33": "https://www.work.ua/jobs/3816156/",
    "34": "https://www.work.ua/jobs/3669112/",
    "35": "https://www.work.ua/jobs/3816048/",
    "36": "https://www.work.ua/jobs/3803560/",
    "37": "https://www.work.ua/jobs/3822990/",
    "38": "https://www.work.ua/jobs/2383336/",
    "39": "https://www.work.ua/jobs/3818571/",
    "40": "https://www.work.ua/jobs/3822226/",
    "41": "https://www.work.ua/jobs/3798547/",
    "42": "https://www.work.ua/jobs/2985750/",
    "43": "https://www.work.ua/jobs/2502450/",
    "44": "https://www.work.ua/jobs/3822320/",
    "45": "https://www.work.ua/jobs/3756297/",
    "46": "https://www.work.ua/jobs/3755682/",
    "47": "https://www.work.ua/jobs/3711003/",
    "48": "https://www.work.ua/jobs/3803178/",
    "49": "https://www.work.ua/jobs/3767239/",
    "50": "https://www.work.ua/jobs/3387290/",
    "51": "https://www.work.ua/jobs/3821130/",
    "52": "https://www.work.ua/jobs/3788622/",
    "53": "https://www.work.ua/jobs/3746407/",
    "54": "https://www.work.ua/jobs/3820904/",
    "55": "https://www.work.ua/jobs/3820809/",
    "56": "https://www.work.ua/jobs/3523665/",
    "57": "https://www.work.ua/jobs/3789511/",
    "58": "https://www.work.ua/jobs/3768927/",
    "59": "https://www.work.ua/jobs/3820515/",
    "60": "https://www.work.ua/jobs/3742490/",
    "61": "https://www.work.ua/jobs/3818937/",
    "62": "https://www.work.ua/jobs/3818853/",
    "63": "https://www.work.ua/jobs/3802703/",
    "64": "https://www.work.ua/jobs/3745418/",
    "65": "https://www.work.ua/jobs/3779877/",
    "66": "https://www.work.ua/jobs/1652790/",
    "67": "https://www.work.ua/jobs/731909/",
    "68": "https://www.work.ua/jobs/2675718/",
    "69": "https://www.work.ua/jobs/3289730/",
    "70": "https://www.work.ua/jobs/3818215/",
    "71": "https://www.work.ua/jobs/3818141/",
    "72": "https://www.work.ua/jobs/3817722/",
    "73": "https://www.work.ua/jobs/2940661/",
    "74": "https://www.work.ua/jobs/3744119/",
    "75": "https://www.work.ua/jobs/3805521/",
    "76": "https://www.work.ua/jobs/2541999/",
    "77": "https://www.work.ua/jobs/3817272/",
    "78": "https://www.work.ua/jobs/3791742/",
    "79": "https://www.work.ua/jobs/2196449/",
    "80": "https://www.work.ua/jobs/3816758/",
    "81": "https://www.work.ua/jobs/3312275/",
    "82": "https://www.work.ua/jobs/3805494/",
    "83": "https://www.work.ua/jobs/3784838/",
    "84": "https://www.work.ua/jobs/3813597/",
    "99": "https://www.work.ua/jobs/3822199/",
    "100": "https://www.work.ua/jobs/3790455/",
    "101": "https://www.work.ua/jobs/3790511/",
    "102": "https://www.work.ua/jobs/3693516/",
    "103": "https://www.work.ua/jobs/3790490/",
    "104": "https://www.work.ua/jobs/3793836/",
    "105": "https://www.work.ua/jobs/3191387/",
    "106": "https://www.work.ua/jobs/3562110/",
    "107": "https://www.work.ua/jobs/3264228/",
    "108": "https://www.work.ua/jobs/3794295/",
    "109": "https://www.work.ua/jobs/3733182/",
    "110": "https://www.work.ua/jobs/3823719/",
    "111": "https://www.work.ua/jobs/2716080/",
    "112": "https://www.work.ua/jobs/3808569/",
    "113": "https://www.work.ua/jobs/3823718/",
    "114": "https://www.work.ua/jobs/3225461/",
    "115": "https://www.work.ua/jobs/3802216/",
    "116": "https://www.work.ua/jobs/3691846/",
    "117": "https://www.work.ua/jobs/3794099/",
    "118": "https://www.work.ua/jobs/3096365/",
    "119": "https://www.work.ua/jobs/3808273/",
    "120": "https://www.work.ua/jobs/3769577/",
    "121": "https://www.work.ua/jobs/3749892/",
    "122": "https://www.work.ua/jobs/3665950/",
    "123": "https://www.work.ua/jobs/3823696/",
    "124": "https://www.work.ua/jobs/3823691/",
    "125": "https://www.work.ua/jobs/3717848/",
    "126": "https://www.work.ua/jobs/3635414/",
    "127": "https://www.work.ua/jobs/3823686/",
    "128": "https://www.work.ua/jobs/3815255/",
    "129": "https://www.work.ua/jobs/3794036/",
    "130": "https://www.work.ua/jobs/3776282/",
    "131": "https://www.work.ua/jobs/3742040/",
    "132": "https://www.work.ua/jobs/3823668/",
    "133": "https://www.work.ua/jobs/3807977/",
    "134": "https://www.work.ua/jobs/2778878/",
    "135": "https://www.work.ua/jobs/3823662/",
    "136": "https://www.work.ua/jobs/3572815/",
    "137": "https://www.work.ua/jobs/3800703/",
    "138": "https://www.work.ua/jobs/3808500/",
    "139": "https://www.work.ua/jobs/3383429/",
    "140": "https://www.work.ua/jobs/3783158/",
    "141": "https://www.work.ua/jobs/3254986/",
    "142": "https://www.work.ua/jobs/3823638/",
    "143": "https://www.work.ua/jobs/3719013/",
    "144": "https://www.work.ua/jobs/3778081/",
    "145": "https://www.work.ua/jobs/3823622/",
    "146": "https://www.work.ua/jobs/3781255/",
    "147": "https://www.work.ua/jobs/3823618/",
    "148": "https://www.work.ua/jobs/3808440/",
    "149": "https://www.work.ua/jobs/3801596/",
    "150": "https://www.work.ua/jobs/3823615/",
    "151": "https://www.work.ua/jobs/3823613/",
    "152": "https://www.work.ua/jobs/2631648/",
    "153": "https://www.work.ua/jobs/3823598/",
    "154": "https://www.work.ua/jobs/3823556/",
    "155": "https://www.work.ua/jobs/3824910/",
    "156": "https://www.work.ua/jobs/3824911/",
    "157": "https://www.work.ua/jobs/3503443/",
    "158": "https://www.work.ua/jobs/3809637/",
    "159": "https://www.work.ua/jobs/3815874/",
    "160": "https://www.work.ua/jobs/3824814/",
    "161": "https://www.work.ua/jobs/3712022/",
    "162": "https://www.work.ua/jobs/3824813/",
    "163": "https://www.work.ua/jobs/3803032/",
    "164": "https://www.work.ua/jobs/2068311/",
    "165": "https://www.work.ua/jobs/3824794/",
    "166": "https://www.work.ua/jobs/3824793/",
    "167": "https://www.work.ua/jobs/3824790/",
    "168": "https://www.work.ua/jobs/3649910/",
    "169": "https://www.work.ua/jobs/2091536/",
    "170": "https://www.work.ua/jobs/3190079/",
    "171": "https://www.work.ua/jobs/3824786/",
    "172": "https://www.work.ua/jobs/3824777/",
    "173": "https://www.work.ua/jobs/3809634/",
    "174": "https://www.work.ua/jobs/3609338/",
    "175": "https://www.work.ua/jobs/3732418/",
    "176": "https://www.work.ua/jobs/3815542/",
    "177": "https://www.work.ua/jobs/3722463/",
    "178": "https://www.work.ua/jobs/3824766/",
    "179": "https://www.work.ua/jobs/3479611/",
    "180": "https://www.work.ua/jobs/3673610/",
    "181": "https://www.work.ua/jobs/3749816/",
    "182": "https://www.work.ua/jobs/3824752/",
    "183": "https://www.work.ua/jobs/3779117/",
    "184": "https://www.work.ua/jobs/3612612/",
    "185": "https://www.work.ua/jobs/3690818/",
    "186": "https://www.work.ua/jobs/3507335/",
    "187": "https://www.work.ua/jobs/3715818/",
    "188": "https://www.work.ua/jobs/3824736/",
    "189": "https://www.work.ua/jobs/3824735/",
    "190": "https://www.work.ua/jobs/3593220/",
    "191": "https://www.work.ua/jobs/3824731/",
    "192": "https://www.work.ua/jobs/3796115/",
    "193": "https://www.work.ua/jobs/3824727/",
    "194": "https://www.work.ua/jobs/3615699/",
    "195": "https://www.work.ua/jobs/3824720/",
    "196": "https://www.work.ua/jobs/2731033/",
    "197": "https://www.work.ua/jobs/3661823/",
    "198": "https://www.work.ua/jobs/3704832/",
    "199": "https://www.work.ua/jobs/2597944/",
    "200": "https://www.work.ua/jobs/1830722/",
    "201": "https://www.work.ua/jobs/3796114/",
    "202": "https://www.work.ua/jobs/3263779/",
    "203": "https://www.work.ua/jobs/3824696/",
    "204": "https://www.work.ua/jobs/3708033/",
    "205": "https://www.work.ua/jobs/3824692/",
    "206": "https://www.work.ua/jobs/3689735/",
    "207": "https://www.work.ua/jobs/3809752/",
    "208": "https://www.work.ua/jobs/3447304/",
    "209": "https://www.work.ua/jobs/3803310/",
    "210": "https://www.work.ua/jobs/1537321/",
    "211": "https://www.work.ua/jobs/3169446/",
    "212": "https://www.work.ua/jobs/3824687/",
    "213": "https://www.work.ua/jobs/3581405/",
    "214": "https://www.work.ua/jobs/3725922/",
    "215": "https://www.work.ua/jobs/3751480/",
    "216": "https://www.work.ua/jobs/3824676/",
    "217": "https://www.work.ua/jobs/3770567/",
    "218": "https://www.work.ua/jobs/3484381/",
    "219": "https://www.work.ua/jobs/3073555/",
    "220": "https://www.work.ua/jobs/3789937/",
    "221": "https://www.work.ua/jobs/3228947/",
    "222": "https://www.work.ua/jobs/3786483/",
    "223": "https://www.work.ua/jobs/3738464/",
    "224": "https://www.work.ua/jobs/3688463/",
    "225": "https://www.work.ua/jobs/3809555/",
    "226": "https://www.work.ua/jobs/3296662/",
    "227": "https://www.work.ua/jobs/3824611/",
    "228": "https://www.work.ua/jobs/3277979/",
    "229": "https://www.work.ua/jobs/3824641/",
    "230": "https://www.work.ua/jobs/3744486/",
    "231": "https://www.work.ua/jobs/3803328/",
    "232": "https://www.work.ua/jobs/41856/",
    "233": "https://www.work.ua/jobs/3795962/",
    "234": "https://www.work.ua/jobs/3795549/",
    "235": "https://www.work.ua/jobs/3773042/",
    "236": "https://www.work.ua/jobs/3635414/",
    "237": "https://www.work.ua/jobs/3824628/",
    "238": "https://www.work.ua/jobs/3345205/",
    "239": "https://www.work.ua/jobs/3824626/",
    "240": "https://www.work.ua/jobs/3824621/",
    "241": "https://www.work.ua/jobs/3774379/",
    "242": "https://www.work.ua/jobs/3824618/",
    "243": "https://www.work.ua/jobs/2410851/",
    "244": "https://www.work.ua/jobs/3666120/",
    "245": "https://www.work.ua/jobs/3116466/",
    "246": "https://www.work.ua/jobs/3803243/",
    "247": "https://www.work.ua/jobs/2645128/",
    "248": "https://www.work.ua/jobs/3816197/",
    "249": "https://www.work.ua/jobs/3815747/",
    "250": "https://www.work.ua/jobs/3025364/",
    "251": "https://www.work.ua/jobs/3816406/",
    "252": "https://www.work.ua/jobs/3736607/",
    "253": "https://www.work.ua/jobs/3824593/",
    "254": "https://www.work.ua/jobs/1712282/",
    "255": "https://www.work.ua/jobs/3824590/",
    "256": "https://www.work.ua/jobs/291782/",
    "257": "https://www.work.ua/jobs/3824580/",
    "258": "https://www.work.ua/jobs/3739662/",
    "259": "https://www.work.ua/jobs/1892235/",
    "260": "https://www.work.ua/jobs/3824570/",
    "261": "https://www.work.ua/jobs/2068296/",
    "262": "https://www.work.ua/jobs/3628414/",
    "263": "https://www.work.ua/jobs/3824562/",
    "264": "https://www.work.ua/jobs/3663565/",
    "265": "https://www.work.ua/jobs/3809901/",
    "266": "https://www.work.ua/jobs/3249796/",
    "267": "https://www.work.ua/jobs/3792739/",
    "268": "https://www.work.ua/jobs/3277549/",
    "269": "https://www.work.ua/jobs/3787089/",
    "270": "https://www.work.ua/jobs/3824544/",
    "271": "https://www.work.ua/jobs/3795923/",
    "272": "https://www.work.ua/jobs/3815712/",
    "273": "https://www.work.ua/jobs/3824529/",
    "274": "https://www.work.ua/jobs/3794309/",
    "275": "https://www.work.ua/jobs/3809868/",
    "276": "https://www.work.ua/jobs/3217834/",
    "277": "https://www.work.ua/jobs/3802945/",
    "278": "https://www.work.ua/jobs/3803327/",
    "279": "https://www.work.ua/jobs/3809690/",
    "280": "https://www.work.ua/jobs/3809479/"
}